jemdoc/__init__.py
jemdoc/main.py
jemdoc/parser.py
jemdoc/cli/__init__.py
jemdoc/cli/commandlineparser.py
jemdoc/cli/defaultconfig.py
jemdoc/control/__init__.py
jemdoc/control/controlstruct.py
jemdoc/control/jandal.py
jemdoc/react/__init__.py
jemdoc/react/reactfactory.py
jemdoc/styling/__init__.py
jemdoc/styling/style.py
jemdoc-0.8.0.dist-info/LICENSE
jemdoc-0.8.0.dist-info/METADATA
jemdoc-0.8.0.dist-info/WHEEL
jemdoc-0.8.0.dist-info/entry_points.txt
jemdoc-0.8.0.dist-info/top_level.txt
jemdoc-0.8.0.dist-info/RECORD
