Metadata-Version: 2.1
Name: jemdoc
Version: 0.8.0
Summary: jemdoc is a light text-based markup language designed for creating websites. It takes a text file written with jemdoc markup, an optional configuration file and an optional menu file, and makes static websites
Home-page: https://github.com/sarpongdk/Jemdoc2.0
Author: David Sarpong
Author-email: sarpong.david2@gmail.com
License: UNKNOWN
Platform: UNKNOWN
Classifier: Programming Language :: Python :: 2
Classifier: Operating System :: OS Independent
Requires-Python: ==2.7.*
Requires-Dist: backports.functools-lru-cache (==1.6.1)
Requires-Dist: beautifulsoup4 (==4.8.2)
Requires-Dist: bs4 (==0.0.1)
Requires-Dist: lesscpy (==0.13.0)
Requires-Dist: libsass (==0.19.4)
Requires-Dist: ply (==3.11)
Requires-Dist: six (==1.14.0)
Requires-Dist: soupsieve (==1.9.5)
